supurr_sdk/Exchange.py
supurr_sdk/__init__.py
supurr_sdk/constants.py
supurr_sdk/utils.py
supurr_sdk-0.1.8.dist-info/METADATA
supurr_sdk-0.1.8.dist-info/WHEEL
supurr_sdk-0.1.8.dist-info/RECORD
